__init__.py
Jonesys_DataTools/JSON_TOOLS/Js_JSON.py
Jonesys_DataTools/JSON_TOOLS/__init__.py
Jonesys_DataTools/databaseProcessors/__init__.py
Jonesys_DataTools/fileProcessors/ILAB_PANDAS.py
Jonesys_DataTools/fileProcessors/__init__.py
jonesys_datatools-0.0.2.dist-info/METADATA
jonesys_datatools-0.0.2.dist-info/WHEEL
jonesys_datatools-0.0.2.dist-info/licenses/LICENSE
jonesys_datatools-0.0.2.dist-info/RECORD
